LNB_MDT/__init__.py
LNB_MDT/config.ini
LNB_MDT/icon.ico
LNB_MDT/main.py
LNB_MDT/main.ui
LNB_MDT/remote_ctl.tcl
LNB_MDT/resources.qrc
LNB_MDT/analysis/__init__.py
LNB_MDT/analysis/analysis_base.py
LNB_MDT/analysis/anisotropy.py
LNB_MDT/analysis/area.py
LNB_MDT/analysis/cluster.py
LNB_MDT/analysis/density.py
LNB_MDT/analysis/gyration.py
LNB_MDT/analysis/height.py
LNB_MDT/analysis/parameter_utils.py
LNB_MDT/analysis/sz.py
LNB_MDT/cases_lnb/lnb.gro
LNB_MDT/cases_lnb/lnb.xtc
LNB_MDT/figure/__init__.py
LNB_MDT/figure/density_figure.py
LNB_MDT/figure/figure.py
LNB_MDT/figure/make_figure.py
LNB_MDT/images/_images/LNB.png
LNB_MDT/images/_images/_PyDracula.png
LNB_MDT/images/_images/_PyDracula_horizontal.png
LNB_MDT/images/icons/cil-3d.png
LNB_MDT/images/icons/cil-4k.png
LNB_MDT/images/icons/cil-account-logout.png
LNB_MDT/images/icons/cil-action-redo.png
LNB_MDT/images/icons/cil-action-undo.png
LNB_MDT/images/icons/cil-airplane-mode-off.png
LNB_MDT/images/icons/cil-airplane-mode.png
LNB_MDT/images/icons/cil-alarm.png
LNB_MDT/images/icons/cil-align-center.png
LNB_MDT/images/icons/cil-align-left.png
LNB_MDT/images/icons/cil-align-right.png
LNB_MDT/images/icons/cil-arrow-bottom-2.png
LNB_MDT/images/icons/cil-arrow-bottom.png
LNB_MDT/images/icons/cil-arrow-circle-bottom.png
LNB_MDT/images/icons/cil-arrow-circle-left.png
LNB_MDT/images/icons/cil-arrow-circle-right.png
LNB_MDT/images/icons/cil-arrow-circle-top.png
LNB_MDT/images/icons/cil-arrow-left.png
LNB_MDT/images/icons/cil-arrow-right.png
LNB_MDT/images/icons/cil-arrow-top.png
LNB_MDT/images/icons/cil-at.png
LNB_MDT/images/icons/cil-av-timer.png
LNB_MDT/images/icons/cil-ban.png
LNB_MDT/images/icons/cil-battery-0.png
LNB_MDT/images/icons/cil-battery-3.png
LNB_MDT/images/icons/cil-battery-5.png
LNB_MDT/images/icons/cil-battery-alert.png
LNB_MDT/images/icons/cil-battery-slash.png
LNB_MDT/images/icons/cil-bell.png
LNB_MDT/images/icons/cil-bluetooth.png
LNB_MDT/images/icons/cil-briefcase.png
LNB_MDT/images/icons/cil-browser.png
lnb_mdt-1.0.1.dist-info/licenses/LICENSE
lnb_mdt-1.0.1.dist-info/METADATA
lnb_mdt-1.0.1.dist-info/WHEEL
lnb_mdt-1.0.1.dist-info/entry_points.txt
lnb_mdt-1.0.1.dist-info/top_level.txt
lnb_mdt-1.0.1.dist-info/RECORD
