Metadata-Version: 2.4
Name: lnb-mdt
Version: 1.0.1
Summary: Lipid Nanobubble Molecular Dynamics Toolkit
Home-page: https://github.com/xinyuren-bio/LNB-MDT
Author: RenXinYU
Author-email: liqianyanqin01@163.com
Project-URL: Bug Reports, https://github.com/xinyuren-bio/LNB-MDT/issues
Project-URL: Source, https://github.com/xinyuren-bio/LNB-MDT
Project-URL: Documentation, https://lnb-mdt.readthedocs.io/
Keywords: molecular-dynamics,lipid,nanobubble,simulation,analysis,mda-analysis
Classifier: Development Status :: 4 - Beta
Classifier: Intended Audience :: Science/Research
Classifier: Topic :: Scientific/Engineering :: Chemistry
Classifier: License :: OSI Approved :: Apache Software License
Classifier: Programming Language :: Python :: 3
Classifier: Programming Language :: Python :: 3.7
Classifier: Programming Language :: Python :: 3.8
Classifier: Programming Language :: Python :: 3.9
Classifier: Programming Language :: Python :: 3.10
Classifier: Programming Language :: Python :: 3.11
Classifier: Operating System :: OS Independent
Requires-Python: >=3.7
License-File: LICENSE
Requires-Dist: cx_Freeze==8.3.0
Requires-Dist: matplotlib==3.10.3
Requires-Dist: MDAnalysis==2.9.0
Requires-Dist: numpy==2.3.1
Requires-Dist: pandas==2.3.0
Requires-Dist: PySide6==6.9.1
Requires-Dist: scipy==1.16.0
Requires-Dist: seaborn==0.13.2
Dynamic: author
Dynamic: author-email
Dynamic: classifier
Dynamic: description
Dynamic: description-content-type
Dynamic: home-page
Dynamic: keywords
Dynamic: license-file
Dynamic: project-url
Dynamic: requires-dist
Dynamic: requires-python
Dynamic: summary
